Metadata-Version: 2.1
Name: appjsonsettings
Version: 0.2.0
Summary: A Python module for easy application settings in JSON format.
Home-page: https://github.com/jacklinquan/appjsonsettings
Author: Quan Lin
Author-email: jacklinquan@gmail.com
License: MIT
Platform: UNKNOWN
Classifier: Development Status :: 3 - Alpha
Classifier: License :: OSI Approved :: MIT License
Classifier: Programming Language :: Python :: 2
Classifier: Programming Language :: Python :: 2.7
Classifier: Programming Language :: Python :: 3
License-File: LICENSE
